lexfeatures/__init__.py
lexfeatures/lexfeature.py
lexfeatures_SaichethanReddy-0.0.1.dist-info/LICENSE
lexfeatures_SaichethanReddy-0.0.1.dist-info/METADATA
lexfeatures_SaichethanReddy-0.0.1.dist-info/WHEEL
lexfeatures_SaichethanReddy-0.0.1.dist-info/top_level.txt
lexfeatures_SaichethanReddy-0.0.1.dist-info/RECORD
