Metadata-Version: 2.1
Name: lexfeatures-SaichethanReddy
Version: 0.0.1
Summary: A wrapper for encoding Lexical features
Home-page: https://github.com/Saichethan/lexfeature/
Author: Saichethan M. Reddy
Author-email: saichethanreddymiriyala@gmail.com
License: UNKNOWN
Platform: UNKNOWN
Classifier: Programming Language :: Python :: 3
Classifier: License :: OSI Approved :: MIT License
Classifier: Operating System :: OS Independent
Requires-Python: >=3.0
